dsml4s8e/__init__.py
dsml4s8e/data_catalog.py
dsml4s8e/define_job.py
dsml4s8e/dotted_catalog_path.py
dsml4s8e/dsmlcatalog/__init__.py
dsml4s8e/dsmlcatalog/dagster_home.py
dsml4s8e/dsmlcatalog/local_storage.py
dsml4s8e/nb_op.py
dsml4s8e/op_params_from_nb.py
dsml4s8e/storage_catalog.py
dsml4s8e/storage_rw/__init__.py
dsml4s8e/storage_rw/pandas_loacl.py
dsml4s8e-0.1.6.dist-info/METADATA
dsml4s8e-0.1.6.dist-info/WHEEL
dsml4s8e-0.1.6.dist-info/RECORD
